{
  "final_standings": [
    "('conservative_bot', 3000, 1)",
    "('random_bot', 0, 2)",
    "('aggressive_bot', 0, 3)"
  ],
  "tournament_duration": 0.004899024963378906,
  "total_hands": 10,
  "settings": {
    "starting_chips": 1000,
    "tournament_type": "freeze_out",
    "blind_levels": "10/20",
    "time_limit": 10.0
  },
  "bot_stats": {
    "conservative_bot": {
      "error_count": 0,
      "timeout_count": 0,
      "is_disqualified": false,
      "max_errors": 5,
      "max_timeouts": 3
    },
    "aggressive_bot": {
      "error_count": 0,
      "timeout_count": 0,
      "is_disqualified": false,
      "max_errors": 5,
      "max_timeouts": 3
    },
    "random_bot": {
      "error_count": 0,
      "timeout_count": 0,
      "is_disqualified": false,
      "max_errors": 5,
      "max_timeouts": 3
    }
  },
  "hand_histories": [
    {
      "hand_number": 1,
      "table_id": 1,
      "players": [
        "aggressive_bot",
        "conservative_bot",
        "random_bot"
      ],
      "starting_chips": {
        "aggressive_bot": 1000,
        "conservative_bot": 1000,
        "random_bot": 1000
      },
      "actions": [
        {
          "player": "aggressive_bot",
          "action": "call",
          "amount": 0,
          "round": "preflop"
        },
        {
          "player": "conservative_bot",
          "action": "fold",
          "amount": 0,
          "round": "preflop"
        }
      ],
      "community_cards": [
        "6\u2663",
        "7\u2660",
        "J\u2660",
        "4\u2660",
        "5\u2666"
      ],
      "results": {
        "winners": [
          "aggressive_bot"
        ],
        "winnings": {
          "aggressive_bot": 50
        },
        "final_chips": {
          "aggressive_bot": 980,
          "conservative_bot": 990,
          "random_bot": 980
        }
      }
    },
    {
      "hand_number": 2,
      "table_id": 1,
      "players": [
        "aggressive_bot",
        "conservative_bot",
        "random_bot"
      ],
      "starting_chips": {
        "aggressive_bot": 1030,
        "conservative_bot": 990,
        "random_bot": 980
      },
      "actions": [
        {
          "player": "aggressive_bot",
          "action": "raise",
          "amount": 50,
          "round": "preflop"
        },
        {
          "player": "conservative_bot",
          "action": "raise",
          "amount": 76,
          "round": "preflop"
        },
        {
          "player": "random_bot",
          "action": "raise",
          "amount": 101,
          "round": "preflop"
        },
        {
          "player": "aggressive_bot",
          "action": "raise",
          "amount": 328,
          "round": "preflop"
        },
        {
          "player": "conservative_bot",
          "action": "raise",
          "amount": 496,
          "round": "preflop"
        },
        {
          "player": "random_bot",
          "action": "raise",
          "amount": 905,
          "round": "preflop"
        },
        {
          "player": "aggressive_bot",
          "action": "call",
          "amount": 0,
          "round": "preflop"
        },
        {
          "player": "conservative_bot",
          "action": "raise",
          "amount": 990,
          "round": "preflop"
        },
        {
          "player": "random_bot",
          "action": "fold",
          "amount": 0,
          "round": "preflop"
        },
        {
          "player": "conservative_bot",
          "action": "check",
          "amount": 0,
          "round": "preflop"
        },
        {
          "player": "aggressive_bot",
          "action": "raise",
          "amount": 1030,
          "round": "preflop"
        }
      ],
      "community_cards": [
        "7\u2660",
        "7\u2663",
        "A\u2666",
        "8\u2665",
        "2\u2660"
      ],
      "results": {
        "winners": [
          "conservative_bot"
        ],
        "winnings": {
          "conservative_bot": 2925
        },
        "final_chips": {
          "aggressive_bot": 0,
          "conservative_bot": 0,
          "random_bot": 75
        }
      }
    },
    {
      "hand_number": 3,
      "table_id": 1,
      "players": [
        "conservative_bot",
        "random_bot"
      ],
      "starting_chips": {
        "conservative_bot": 2925,
        "random_bot": 75
      },
      "actions": [
        {
          "player": "conservative_bot",
          "action": "fold",
          "amount": 0,
          "round": "preflop"
        }
      ],
      "community_cards": [],
      "results": {
        "winners": [
          "random_bot"
        ],
        "winnings": {
          "random_bot": 30
        },
        "final_chips": {
          "conservative_bot": 2905,
          "random_bot": 65
        }
      }
    },
    {
      "hand_number": 4,
      "table_id": 1,
      "players": [
        "conservative_bot",
        "random_bot"
      ],
      "starting_chips": {
        "conservative_bot": 2905,
        "random_bot": 95
      },
      "actions": [
        {
          "player": "conservative_bot",
          "action": "fold",
          "amount": 0,
          "round": "preflop"
        }
      ],
      "community_cards": [],
      "results": {
        "winners": [
          "random_bot"
        ],
        "winnings": {
          "random_bot": 30
        },
        "final_chips": {
          "conservative_bot": 2885,
          "random_bot": 85
        }
      }
    },
    {
      "hand_number": 5,
      "table_id": 1,
      "players": [
        "conservative_bot",
        "random_bot"
      ],
      "starting_chips": {
        "conservative_bot": 2885,
        "random_bot": 115
      },
      "actions": [
        {
          "player": "conservative_bot",
          "action": "raise",
          "amount": 40,
          "round": "preflop"
        },
        {
          "player": "random_bot",
          "action": "fold",
          "amount": 0,
          "round": "preflop"
        }
      ],
      "community_cards": [],
      "results": {
        "winners": [
          "conservative_bot"
        ],
        "winnings": {
          "conservative_bot": 50
        },
        "final_chips": {
          "conservative_bot": 2845,
          "random_bot": 105
        }
      }
    },
    {
      "hand_number": 6,
      "table_id": 1,
      "players": [
        "conservative_bot",
        "random_bot"
      ],
      "starting_chips": {
        "conservative_bot": 2895,
        "random_bot": 105
      },
      "actions": [
        {
          "player": "conservative_bot",
          "action": "fold",
          "amount": 0,
          "round": "preflop"
        }
      ],
      "community_cards": [],
      "results": {
        "winners": [
          "random_bot"
        ],
        "winnings": {
          "random_bot": 30
        },
        "final_chips": {
          "conservative_bot": 2875,
          "random_bot": 95
        }
      }
    },
    {
      "hand_number": 7,
      "table_id": 1,
      "players": [
        "conservative_bot",
        "random_bot"
      ],
      "starting_chips": {
        "conservative_bot": 2875,
        "random_bot": 125
      },
      "actions": [
        {
          "player": "conservative_bot",
          "action": "raise",
          "amount": 40,
          "round": "preflop"
        },
        {
          "player": "random_bot",
          "action": "all_in",
          "amount": 0,
          "round": "preflop"
        },
        {
          "player": "conservative_bot",
          "action": "raise",
          "amount": 180,
          "round": "preflop"
        }
      ],
      "community_cards": [
        "7\u2660",
        "5\u2660",
        "3\u2665",
        "Q\u2666",
        "A\u2660"
      ],
      "results": {
        "winners": [
          "random_bot"
        ],
        "winnings": {
          "random_bot": 305
        },
        "final_chips": {
          "conservative_bot": 2695,
          "random_bot": 0
        }
      }
    },
    {
      "hand_number": 8,
      "table_id": 1,
      "players": [
        "conservative_bot",
        "random_bot"
      ],
      "starting_chips": {
        "conservative_bot": 2695,
        "random_bot": 305
      },
      "actions": [
        {
          "player": "conservative_bot",
          "action": "fold",
          "amount": 0,
          "round": "preflop"
        }
      ],
      "community_cards": [],
      "results": {
        "winners": [
          "random_bot"
        ],
        "winnings": {
          "random_bot": 30
        },
        "final_chips": {
          "conservative_bot": 2675,
          "random_bot": 295
        }
      }
    },
    {
      "hand_number": 9,
      "table_id": 1,
      "players": [
        "conservative_bot",
        "random_bot"
      ],
      "starting_chips": {
        "conservative_bot": 2675,
        "random_bot": 325
      },
      "actions": [
        {
          "player": "conservative_bot",
          "action": "fold",
          "amount": 0,
          "round": "preflop"
        }
      ],
      "community_cards": [],
      "results": {
        "winners": [
          "random_bot"
        ],
        "winnings": {
          "random_bot": 30
        },
        "final_chips": {
          "conservative_bot": 2655,
          "random_bot": 315
        }
      }
    },
    {
      "hand_number": 10,
      "table_id": 1,
      "players": [
        "conservative_bot",
        "random_bot"
      ],
      "starting_chips": {
        "conservative_bot": 2655,
        "random_bot": 345
      },
      "actions": [
        {
          "player": "conservative_bot",
          "action": "raise",
          "amount": 40,
          "round": "preflop"
        },
        {
          "player": "random_bot",
          "action": "all_in",
          "amount": 0,
          "round": "preflop"
        },
        {
          "player": "conservative_bot",
          "action": "raise",
          "amount": 473,
          "round": "preflop"
        }
      ],
      "community_cards": [
        "4\u2660",
        "A\u2660",
        "2\u2665",
        "6\u2665",
        "K\u2660"
      ],
      "results": {
        "winners": [
          "conservative_bot"
        ],
        "winnings": {
          "conservative_bot": 818
        },
        "final_chips": {
          "conservative_bot": 2182,
          "random_bot": 0
        }
      }
    }
  ]
}