{
  "final_standings": [
    "('random_bot', 3000, 1)",
    "('conservative_bot', 0, 2)",
    "('aggressive_bot', 0, 3)"
  ],
  "tournament_duration": 0.017503023147583008,
  "total_hands": 64,
  "settings": {
    "starting_chips": 1000,
    "tournament_type": "freeze_out",
    "blind_levels": "10/20",
    "time_limit": 10.0
  },
  "bot_stats": {
    "conservative_bot": {
      "error_count": 0,
      "timeout_count": 0,
      "is_disqualified": false,
      "max_errors": 5,
      "max_timeouts": 3
    },
    "aggressive_bot": {
      "error_count": 0,
      "timeout_count": 0,
      "is_disqualified": false,
      "max_errors": 5,
      "max_timeouts": 3
    },
    "random_bot": {
      "error_count": 0,
      "timeout_count": 0,
      "is_disqualified": false,
      "max_errors": 5,
      "max_timeouts": 3
    }
  },
  "hand_histories": [
    {
      "hand_number": 15,
      "table_id": 1,
      "players": [
        "conservative_bot",
        "random_bot"
      ],
      "starting_chips": {
        "conservative_bot": 960,
        "random_bot": 2040
      },
      "actions": [
        {
          "player": "conservative_bot",
          "action": "fold",
          "amount": 0,
          "round": "preflop"
        }
      ],
      "community_cards": [],
      "results": {
        "winners": [
          "random_bot"
        ],
        "winnings": {
          "random_bot": 30
        },
        "final_chips": {
          "conservative_bot": 940,
          "random_bot": 2030
        }
      }
    },
    {
      "hand_number": 16,
      "table_id": 1,
      "players": [
        "conservative_bot",
        "random_bot"
      ],
      "starting_chips": {
        "conservative_bot": 940,
        "random_bot": 2060
      },
      "actions": [
        {
          "player": "conservative_bot",
          "action": "fold",
          "amount": 0,
          "round": "preflop"
        }
      ],
      "community_cards": [],
      "results": {
        "winners": [
          "random_bot"
        ],
        "winnings": {
          "random_bot": 30
        },
        "final_chips": {
          "conservative_bot": 920,
          "random_bot": 2050
        }
      }
    },
    {
      "hand_number": 17,
      "table_id": 1,
      "players": [
        "conservative_bot",
        "random_bot"
      ],
      "starting_chips": {
        "conservative_bot": 920,
        "random_bot": 2080
      },
      "actions": [
        {
          "player": "conservative_bot",
          "action": "fold",
          "amount": 0,
          "round": "preflop"
        }
      ],
      "community_cards": [],
      "results": {
        "winners": [
          "random_bot"
        ],
        "winnings": {
          "random_bot": 30
        },
        "final_chips": {
          "conservative_bot": 900,
          "random_bot": 2070
        }
      }
    },
    {
      "hand_number": 18,
      "table_id": 1,
      "players": [
        "conservative_bot",
        "random_bot"
      ],
      "starting_chips": {
        "conservative_bot": 900,
        "random_bot": 2100
      },
      "actions": [
        {
          "player": "conservative_bot",
          "action": "fold",
          "amount": 0,
          "round": "preflop"
        }
      ],
      "community_cards": [],
      "results": {
        "winners": [
          "random_bot"
        ],
        "winnings": {
          "random_bot": 30
        },
        "final_chips": {
          "conservative_bot": 880,
          "random_bot": 2090
        }
      }
    },
    {
      "hand_number": 19,
      "table_id": 1,
      "players": [
        "conservative_bot",
        "random_bot"
      ],
      "starting_chips": {
        "conservative_bot": 880,
        "random_bot": 2120
      },
      "actions": [
        {
          "player": "conservative_bot",
          "action": "fold",
          "amount": 0,
          "round": "preflop"
        }
      ],
      "community_cards": [],
      "results": {
        "winners": [
          "random_bot"
        ],
        "winnings": {
          "random_bot": 30
        },
        "final_chips": {
          "conservative_bot": 860,
          "random_bot": 2110
        }
      }
    },
    {
      "hand_number": 20,
      "table_id": 1,
      "players": [
        "conservative_bot",
        "random_bot"
      ],
      "starting_chips": {
        "conservative_bot": 860,
        "random_bot": 2140
      },
      "actions": [
        {
          "player": "conservative_bot",
          "action": "fold",
          "amount": 0,
          "round": "preflop"
        }
      ],
      "community_cards": [],
      "results": {
        "winners": [
          "random_bot"
        ],
        "winnings": {
          "random_bot": 30
        },
        "final_chips": {
          "conservative_bot": 840,
          "random_bot": 2130
        }
      }
    },
    {
      "hand_number": 21,
      "table_id": 1,
      "players": [
        "conservative_bot",
        "random_bot"
      ],
      "starting_chips": {
        "conservative_bot": 840,
        "random_bot": 2160
      },
      "actions": [
        {
          "player": "conservative_bot",
          "action": "fold",
          "amount": 0,
          "round": "preflop"
        }
      ],
      "community_cards": [],
      "results": {
        "winners": [
          "random_bot"
        ],
        "winnings": {
          "random_bot": 30
        },
        "final_chips": {
          "conservative_bot": 820,
          "random_bot": 2150
        }
      }
    },
    {
      "hand_number": 22,
      "table_id": 1,
      "players": [
        "conservative_bot",
        "random_bot"
      ],
      "starting_chips": {
        "conservative_bot": 820,
        "random_bot": 2180
      },
      "actions": [
        {
          "player": "conservative_bot",
          "action": "fold",
          "amount": 0,
          "round": "preflop"
        }
      ],
      "community_cards": [],
      "results": {
        "winners": [
          "random_bot"
        ],
        "winnings": {
          "random_bot": 30
        },
        "final_chips": {
          "conservative_bot": 800,
          "random_bot": 2170
        }
      }
    },
    {
      "hand_number": 23,
      "table_id": 1,
      "players": [
        "conservative_bot",
        "random_bot"
      ],
      "starting_chips": {
        "conservative_bot": 800,
        "random_bot": 2200
      },
      "actions": [
        {
          "player": "conservative_bot",
          "action": "fold",
          "amount": 0,
          "round": "preflop"
        }
      ],
      "community_cards": [],
      "results": {
        "winners": [
          "random_bot"
        ],
        "winnings": {
          "random_bot": 30
        },
        "final_chips": {
          "conservative_bot": 780,
          "random_bot": 2190
        }
      }
    },
    {
      "hand_number": 24,
      "table_id": 1,
      "players": [
        "conservative_bot",
        "random_bot"
      ],
      "starting_chips": {
        "conservative_bot": 780,
        "random_bot": 2220
      },
      "actions": [
        {
          "player": "conservative_bot",
          "action": "fold",
          "amount": 0,
          "round": "preflop"
        }
      ],
      "community_cards": [],
      "results": {
        "winners": [
          "random_bot"
        ],
        "winnings": {
          "random_bot": 30
        },
        "final_chips": {
          "conservative_bot": 760,
          "random_bot": 2210
        }
      }
    },
    {
      "hand_number": 25,
      "table_id": 1,
      "players": [
        "conservative_bot",
        "random_bot"
      ],
      "starting_chips": {
        "conservative_bot": 760,
        "random_bot": 2240
      },
      "actions": [
        {
          "player": "conservative_bot",
          "action": "fold",
          "amount": 0,
          "round": "preflop"
        }
      ],
      "community_cards": [],
      "results": {
        "winners": [
          "random_bot"
        ],
        "winnings": {
          "random_bot": 30
        },
        "final_chips": {
          "conservative_bot": 740,
          "random_bot": 2230
        }
      }
    },
    {
      "hand_number": 26,
      "table_id": 1,
      "players": [
        "conservative_bot",
        "random_bot"
      ],
      "starting_chips": {
        "conservative_bot": 740,
        "random_bot": 2260
      },
      "actions": [
        {
          "player": "conservative_bot",
          "action": "fold",
          "amount": 0,
          "round": "preflop"
        }
      ],
      "community_cards": [],
      "results": {
        "winners": [
          "random_bot"
        ],
        "winnings": {
          "random_bot": 30
        },
        "final_chips": {
          "conservative_bot": 720,
          "random_bot": 2250
        }
      }
    },
    {
      "hand_number": 27,
      "table_id": 1,
      "players": [
        "conservative_bot",
        "random_bot"
      ],
      "starting_chips": {
        "conservative_bot": 720,
        "random_bot": 2280
      },
      "actions": [
        {
          "player": "conservative_bot",
          "action": "fold",
          "amount": 0,
          "round": "preflop"
        }
      ],
      "community_cards": [],
      "results": {
        "winners": [
          "random_bot"
        ],
        "winnings": {
          "random_bot": 30
        },
        "final_chips": {
          "conservative_bot": 700,
          "random_bot": 2270
        }
      }
    },
    {
      "hand_number": 28,
      "table_id": 1,
      "players": [
        "conservative_bot",
        "random_bot"
      ],
      "starting_chips": {
        "conservative_bot": 700,
        "random_bot": 2300
      },
      "actions": [
        {
          "player": "conservative_bot",
          "action": "fold",
          "amount": 0,
          "round": "preflop"
        }
      ],
      "community_cards": [],
      "results": {
        "winners": [
          "random_bot"
        ],
        "winnings": {
          "random_bot": 30
        },
        "final_chips": {
          "conservative_bot": 680,
          "random_bot": 2290
        }
      }
    },
    {
      "hand_number": 29,
      "table_id": 1,
      "players": [
        "conservative_bot",
        "random_bot"
      ],
      "starting_chips": {
        "conservative_bot": 680,
        "random_bot": 2320
      },
      "actions": [
        {
          "player": "conservative_bot",
          "action": "fold",
          "amount": 0,
          "round": "preflop"
        }
      ],
      "community_cards": [],
      "results": {
        "winners": [
          "random_bot"
        ],
        "winnings": {
          "random_bot": 30
        },
        "final_chips": {
          "conservative_bot": 660,
          "random_bot": 2310
        }
      }
    },
    {
      "hand_number": 30,
      "table_id": 1,
      "players": [
        "conservative_bot",
        "random_bot"
      ],
      "starting_chips": {
        "conservative_bot": 660,
        "random_bot": 2340
      },
      "actions": [
        {
          "player": "conservative_bot",
          "action": "fold",
          "amount": 0,
          "round": "preflop"
        }
      ],
      "community_cards": [],
      "results": {
        "winners": [
          "random_bot"
        ],
        "winnings": {
          "random_bot": 30
        },
        "final_chips": {
          "conservative_bot": 640,
          "random_bot": 2330
        }
      }
    },
    {
      "hand_number": 31,
      "table_id": 1,
      "players": [
        "conservative_bot",
        "random_bot"
      ],
      "starting_chips": {
        "conservative_bot": 640,
        "random_bot": 2360
      },
      "actions": [
        {
          "player": "conservative_bot",
          "action": "fold",
          "amount": 0,
          "round": "preflop"
        }
      ],
      "community_cards": [],
      "results": {
        "winners": [
          "random_bot"
        ],
        "winnings": {
          "random_bot": 30
        },
        "final_chips": {
          "conservative_bot": 620,
          "random_bot": 2350
        }
      }
    },
    {
      "hand_number": 32,
      "table_id": 1,
      "players": [
        "conservative_bot",
        "random_bot"
      ],
      "starting_chips": {
        "conservative_bot": 620,
        "random_bot": 2380
      },
      "actions": [
        {
          "player": "conservative_bot",
          "action": "fold",
          "amount": 0,
          "round": "preflop"
        }
      ],
      "community_cards": [],
      "results": {
        "winners": [
          "random_bot"
        ],
        "winnings": {
          "random_bot": 30
        },
        "final_chips": {
          "conservative_bot": 600,
          "random_bot": 2370
        }
      }
    },
    {
      "hand_number": 33,
      "table_id": 1,
      "players": [
        "conservative_bot",
        "random_bot"
      ],
      "starting_chips": {
        "conservative_bot": 600,
        "random_bot": 2400
      },
      "actions": [
        {
          "player": "conservative_bot",
          "action": "fold",
          "amount": 0,
          "round": "preflop"
        }
      ],
      "community_cards": [],
      "results": {
        "winners": [
          "random_bot"
        ],
        "winnings": {
          "random_bot": 30
        },
        "final_chips": {
          "conservative_bot": 580,
          "random_bot": 2390
        }
      }
    },
    {
      "hand_number": 34,
      "table_id": 1,
      "players": [
        "conservative_bot",
        "random_bot"
      ],
      "starting_chips": {
        "conservative_bot": 580,
        "random_bot": 2420
      },
      "actions": [
        {
          "player": "conservative_bot",
          "action": "fold",
          "amount": 0,
          "round": "preflop"
        }
      ],
      "community_cards": [],
      "results": {
        "winners": [
          "random_bot"
        ],
        "winnings": {
          "random_bot": 30
        },
        "final_chips": {
          "conservative_bot": 560,
          "random_bot": 2410
        }
      }
    },
    {
      "hand_number": 35,
      "table_id": 1,
      "players": [
        "conservative_bot",
        "random_bot"
      ],
      "starting_chips": {
        "conservative_bot": 560,
        "random_bot": 2440
      },
      "actions": [
        {
          "player": "conservative_bot",
          "action": "fold",
          "amount": 0,
          "round": "preflop"
        }
      ],
      "community_cards": [],
      "results": {
        "winners": [
          "random_bot"
        ],
        "winnings": {
          "random_bot": 30
        },
        "final_chips": {
          "conservative_bot": 540,
          "random_bot": 2430
        }
      }
    },
    {
      "hand_number": 36,
      "table_id": 1,
      "players": [
        "conservative_bot",
        "random_bot"
      ],
      "starting_chips": {
        "conservative_bot": 540,
        "random_bot": 2460
      },
      "actions": [
        {
          "player": "conservative_bot",
          "action": "fold",
          "amount": 0,
          "round": "preflop"
        }
      ],
      "community_cards": [],
      "results": {
        "winners": [
          "random_bot"
        ],
        "winnings": {
          "random_bot": 30
        },
        "final_chips": {
          "conservative_bot": 520,
          "random_bot": 2450
        }
      }
    },
    {
      "hand_number": 37,
      "table_id": 1,
      "players": [
        "conservative_bot",
        "random_bot"
      ],
      "starting_chips": {
        "conservative_bot": 520,
        "random_bot": 2480
      },
      "actions": [
        {
          "player": "conservative_bot",
          "action": "fold",
          "amount": 0,
          "round": "preflop"
        }
      ],
      "community_cards": [],
      "results": {
        "winners": [
          "random_bot"
        ],
        "winnings": {
          "random_bot": 30
        },
        "final_chips": {
          "conservative_bot": 500,
          "random_bot": 2470
        }
      }
    },
    {
      "hand_number": 38,
      "table_id": 1,
      "players": [
        "conservative_bot",
        "random_bot"
      ],
      "starting_chips": {
        "conservative_bot": 500,
        "random_bot": 2500
      },
      "actions": [
        {
          "player": "conservative_bot",
          "action": "fold",
          "amount": 0,
          "round": "preflop"
        }
      ],
      "community_cards": [],
      "results": {
        "winners": [
          "random_bot"
        ],
        "winnings": {
          "random_bot": 30
        },
        "final_chips": {
          "conservative_bot": 480,
          "random_bot": 2490
        }
      }
    },
    {
      "hand_number": 39,
      "table_id": 1,
      "players": [
        "conservative_bot",
        "random_bot"
      ],
      "starting_chips": {
        "conservative_bot": 480,
        "random_bot": 2520
      },
      "actions": [
        {
          "player": "conservative_bot",
          "action": "fold",
          "amount": 0,
          "round": "preflop"
        }
      ],
      "community_cards": [],
      "results": {
        "winners": [
          "random_bot"
        ],
        "winnings": {
          "random_bot": 30
        },
        "final_chips": {
          "conservative_bot": 460,
          "random_bot": 2510
        }
      }
    },
    {
      "hand_number": 40,
      "table_id": 1,
      "players": [
        "conservative_bot",
        "random_bot"
      ],
      "starting_chips": {
        "conservative_bot": 460,
        "random_bot": 2540
      },
      "actions": [
        {
          "player": "conservative_bot",
          "action": "fold",
          "amount": 0,
          "round": "preflop"
        }
      ],
      "community_cards": [],
      "results": {
        "winners": [
          "random_bot"
        ],
        "winnings": {
          "random_bot": 30
        },
        "final_chips": {
          "conservative_bot": 440,
          "random_bot": 2530
        }
      }
    },
    {
      "hand_number": 41,
      "table_id": 1,
      "players": [
        "conservative_bot",
        "random_bot"
      ],
      "starting_chips": {
        "conservative_bot": 440,
        "random_bot": 2560
      },
      "actions": [
        {
          "player": "conservative_bot",
          "action": "fold",
          "amount": 0,
          "round": "preflop"
        }
      ],
      "community_cards": [],
      "results": {
        "winners": [
          "random_bot"
        ],
        "winnings": {
          "random_bot": 30
        },
        "final_chips": {
          "conservative_bot": 420,
          "random_bot": 2550
        }
      }
    },
    {
      "hand_number": 42,
      "table_id": 1,
      "players": [
        "conservative_bot",
        "random_bot"
      ],
      "starting_chips": {
        "conservative_bot": 420,
        "random_bot": 2580
      },
      "actions": [
        {
          "player": "conservative_bot",
          "action": "raise",
          "amount": 40,
          "round": "preflop"
        },
        {
          "player": "random_bot",
          "action": "call",
          "amount": 0,
          "round": "preflop"
        }
      ],
      "community_cards": [
        "7\u2665",
        "3\u2660",
        "9\u2663",
        "3\u2666",
        "9\u2666"
      ],
      "results": {
        "winners": [
          "conservative_bot"
        ],
        "winnings": {
          "conservative_bot": 80
        },
        "final_chips": {
          "conservative_bot": 380,
          "random_bot": 2540
        }
      }
    },
    {
      "hand_number": 43,
      "table_id": 1,
      "players": [
        "conservative_bot",
        "random_bot"
      ],
      "starting_chips": {
        "conservative_bot": 460,
        "random_bot": 2540
      },
      "actions": [
        {
          "player": "conservative_bot",
          "action": "fold",
          "amount": 0,
          "round": "preflop"
        }
      ],
      "community_cards": [],
      "results": {
        "winners": [
          "random_bot"
        ],
        "winnings": {
          "random_bot": 30
        },
        "final_chips": {
          "conservative_bot": 440,
          "random_bot": 2530
        }
      }
    },
    {
      "hand_number": 44,
      "table_id": 1,
      "players": [
        "conservative_bot",
        "random_bot"
      ],
      "starting_chips": {
        "conservative_bot": 440,
        "random_bot": 2560
      },
      "actions": [
        {
          "player": "conservative_bot",
          "action": "fold",
          "amount": 0,
          "round": "preflop"
        }
      ],
      "community_cards": [],
      "results": {
        "winners": [
          "random_bot"
        ],
        "winnings": {
          "random_bot": 30
        },
        "final_chips": {
          "conservative_bot": 420,
          "random_bot": 2550
        }
      }
    },
    {
      "hand_number": 45,
      "table_id": 1,
      "players": [
        "conservative_bot",
        "random_bot"
      ],
      "starting_chips": {
        "conservative_bot": 420,
        "random_bot": 2580
      },
      "actions": [
        {
          "player": "conservative_bot",
          "action": "fold",
          "amount": 0,
          "round": "preflop"
        }
      ],
      "community_cards": [],
      "results": {
        "winners": [
          "random_bot"
        ],
        "winnings": {
          "random_bot": 30
        },
        "final_chips": {
          "conservative_bot": 400,
          "random_bot": 2570
        }
      }
    },
    {
      "hand_number": 46,
      "table_id": 1,
      "players": [
        "conservative_bot",
        "random_bot"
      ],
      "starting_chips": {
        "conservative_bot": 400,
        "random_bot": 2600
      },
      "actions": [
        {
          "player": "conservative_bot",
          "action": "fold",
          "amount": 0,
          "round": "preflop"
        }
      ],
      "community_cards": [],
      "results": {
        "winners": [
          "random_bot"
        ],
        "winnings": {
          "random_bot": 30
        },
        "final_chips": {
          "conservative_bot": 380,
          "random_bot": 2590
        }
      }
    },
    {
      "hand_number": 47,
      "table_id": 1,
      "players": [
        "conservative_bot",
        "random_bot"
      ],
      "starting_chips": {
        "conservative_bot": 380,
        "random_bot": 2620
      },
      "actions": [
        {
          "player": "conservative_bot",
          "action": "fold",
          "amount": 0,
          "round": "preflop"
        }
      ],
      "community_cards": [],
      "results": {
        "winners": [
          "random_bot"
        ],
        "winnings": {
          "random_bot": 30
        },
        "final_chips": {
          "conservative_bot": 360,
          "random_bot": 2610
        }
      }
    },
    {
      "hand_number": 48,
      "table_id": 1,
      "players": [
        "conservative_bot",
        "random_bot"
      ],
      "starting_chips": {
        "conservative_bot": 360,
        "random_bot": 2640
      },
      "actions": [
        {
          "player": "conservative_bot",
          "action": "fold",
          "amount": 0,
          "round": "preflop"
        }
      ],
      "community_cards": [],
      "results": {
        "winners": [
          "random_bot"
        ],
        "winnings": {
          "random_bot": 30
        },
        "final_chips": {
          "conservative_bot": 340,
          "random_bot": 2630
        }
      }
    },
    {
      "hand_number": 49,
      "table_id": 1,
      "players": [
        "conservative_bot",
        "random_bot"
      ],
      "starting_chips": {
        "conservative_bot": 340,
        "random_bot": 2660
      },
      "actions": [
        {
          "player": "conservative_bot",
          "action": "fold",
          "amount": 0,
          "round": "preflop"
        }
      ],
      "community_cards": [],
      "results": {
        "winners": [
          "random_bot"
        ],
        "winnings": {
          "random_bot": 30
        },
        "final_chips": {
          "conservative_bot": 320,
          "random_bot": 2650
        }
      }
    },
    {
      "hand_number": 50,
      "table_id": 1,
      "players": [
        "conservative_bot",
        "random_bot"
      ],
      "starting_chips": {
        "conservative_bot": 320,
        "random_bot": 2680
      },
      "actions": [
        {
          "player": "conservative_bot",
          "action": "fold",
          "amount": 0,
          "round": "preflop"
        }
      ],
      "community_cards": [],
      "results": {
        "winners": [
          "random_bot"
        ],
        "winnings": {
          "random_bot": 30
        },
        "final_chips": {
          "conservative_bot": 300,
          "random_bot": 2670
        }
      }
    },
    {
      "hand_number": 51,
      "table_id": 1,
      "players": [
        "conservative_bot",
        "random_bot"
      ],
      "starting_chips": {
        "conservative_bot": 300,
        "random_bot": 2700
      },
      "actions": [
        {
          "player": "conservative_bot",
          "action": "fold",
          "amount": 0,
          "round": "preflop"
        }
      ],
      "community_cards": [],
      "results": {
        "winners": [
          "random_bot"
        ],
        "winnings": {
          "random_bot": 30
        },
        "final_chips": {
          "conservative_bot": 280,
          "random_bot": 2690
        }
      }
    },
    {
      "hand_number": 52,
      "table_id": 1,
      "players": [
        "conservative_bot",
        "random_bot"
      ],
      "starting_chips": {
        "conservative_bot": 280,
        "random_bot": 2720
      },
      "actions": [
        {
          "player": "conservative_bot",
          "action": "raise",
          "amount": 40,
          "round": "preflop"
        },
        {
          "player": "random_bot",
          "action": "all_in",
          "amount": 0,
          "round": "preflop"
        },
        {
          "player": "conservative_bot",
          "action": "fold",
          "amount": 0,
          "round": "preflop"
        }
      ],
      "community_cards": [],
      "results": {
        "winners": [
          "random_bot"
        ],
        "winnings": {
          "random_bot": 2760
        },
        "final_chips": {
          "conservative_bot": 240,
          "random_bot": 0
        }
      }
    },
    {
      "hand_number": 53,
      "table_id": 1,
      "players": [
        "conservative_bot",
        "random_bot"
      ],
      "starting_chips": {
        "conservative_bot": 240,
        "random_bot": 2760
      },
      "actions": [
        {
          "player": "conservative_bot",
          "action": "fold",
          "amount": 0,
          "round": "preflop"
        }
      ],
      "community_cards": [],
      "results": {
        "winners": [
          "random_bot"
        ],
        "winnings": {
          "random_bot": 30
        },
        "final_chips": {
          "conservative_bot": 220,
          "random_bot": 2750
        }
      }
    },
    {
      "hand_number": 54,
      "table_id": 1,
      "players": [
        "conservative_bot",
        "random_bot"
      ],
      "starting_chips": {
        "conservative_bot": 220,
        "random_bot": 2780
      },
      "actions": [
        {
          "player": "conservative_bot",
          "action": "fold",
          "amount": 0,
          "round": "preflop"
        }
      ],
      "community_cards": [],
      "results": {
        "winners": [
          "random_bot"
        ],
        "winnings": {
          "random_bot": 30
        },
        "final_chips": {
          "conservative_bot": 200,
          "random_bot": 2770
        }
      }
    },
    {
      "hand_number": 55,
      "table_id": 1,
      "players": [
        "conservative_bot",
        "random_bot"
      ],
      "starting_chips": {
        "conservative_bot": 200,
        "random_bot": 2800
      },
      "actions": [
        {
          "player": "conservative_bot",
          "action": "fold",
          "amount": 0,
          "round": "preflop"
        }
      ],
      "community_cards": [],
      "results": {
        "winners": [
          "random_bot"
        ],
        "winnings": {
          "random_bot": 30
        },
        "final_chips": {
          "conservative_bot": 180,
          "random_bot": 2790
        }
      }
    },
    {
      "hand_number": 56,
      "table_id": 1,
      "players": [
        "conservative_bot",
        "random_bot"
      ],
      "starting_chips": {
        "conservative_bot": 180,
        "random_bot": 2820
      },
      "actions": [
        {
          "player": "conservative_bot",
          "action": "fold",
          "amount": 0,
          "round": "preflop"
        }
      ],
      "community_cards": [],
      "results": {
        "winners": [
          "random_bot"
        ],
        "winnings": {
          "random_bot": 30
        },
        "final_chips": {
          "conservative_bot": 160,
          "random_bot": 2810
        }
      }
    },
    {
      "hand_number": 57,
      "table_id": 1,
      "players": [
        "conservative_bot",
        "random_bot"
      ],
      "starting_chips": {
        "conservative_bot": 160,
        "random_bot": 2840
      },
      "actions": [
        {
          "player": "conservative_bot",
          "action": "fold",
          "amount": 0,
          "round": "preflop"
        }
      ],
      "community_cards": [],
      "results": {
        "winners": [
          "random_bot"
        ],
        "winnings": {
          "random_bot": 30
        },
        "final_chips": {
          "conservative_bot": 140,
          "random_bot": 2830
        }
      }
    },
    {
      "hand_number": 58,
      "table_id": 1,
      "players": [
        "conservative_bot",
        "random_bot"
      ],
      "starting_chips": {
        "conservative_bot": 140,
        "random_bot": 2860
      },
      "actions": [
        {
          "player": "conservative_bot",
          "action": "fold",
          "amount": 0,
          "round": "preflop"
        }
      ],
      "community_cards": [],
      "results": {
        "winners": [
          "random_bot"
        ],
        "winnings": {
          "random_bot": 30
        },
        "final_chips": {
          "conservative_bot": 120,
          "random_bot": 2850
        }
      }
    },
    {
      "hand_number": 59,
      "table_id": 1,
      "players": [
        "conservative_bot",
        "random_bot"
      ],
      "starting_chips": {
        "conservative_bot": 120,
        "random_bot": 2880
      },
      "actions": [
        {
          "player": "conservative_bot",
          "action": "fold",
          "amount": 0,
          "round": "preflop"
        }
      ],
      "community_cards": [],
      "results": {
        "winners": [
          "random_bot"
        ],
        "winnings": {
          "random_bot": 30
        },
        "final_chips": {
          "conservative_bot": 100,
          "random_bot": 2870
        }
      }
    },
    {
      "hand_number": 60,
      "table_id": 1,
      "players": [
        "conservative_bot",
        "random_bot"
      ],
      "starting_chips": {
        "conservative_bot": 100,
        "random_bot": 2900
      },
      "actions": [
        {
          "player": "conservative_bot",
          "action": "fold",
          "amount": 0,
          "round": "preflop"
        }
      ],
      "community_cards": [],
      "results": {
        "winners": [
          "random_bot"
        ],
        "winnings": {
          "random_bot": 30
        },
        "final_chips": {
          "conservative_bot": 80,
          "random_bot": 2890
        }
      }
    },
    {
      "hand_number": 61,
      "table_id": 1,
      "players": [
        "conservative_bot",
        "random_bot"
      ],
      "starting_chips": {
        "conservative_bot": 80,
        "random_bot": 2920
      },
      "actions": [
        {
          "player": "conservative_bot",
          "action": "fold",
          "amount": 0,
          "round": "preflop"
        }
      ],
      "community_cards": [],
      "results": {
        "winners": [
          "random_bot"
        ],
        "winnings": {
          "random_bot": 30
        },
        "final_chips": {
          "conservative_bot": 60,
          "random_bot": 2910
        }
      }
    },
    {
      "hand_number": 62,
      "table_id": 1,
      "players": [
        "conservative_bot",
        "random_bot"
      ],
      "starting_chips": {
        "conservative_bot": 60,
        "random_bot": 2940
      },
      "actions": [
        {
          "player": "conservative_bot",
          "action": "fold",
          "amount": 0,
          "round": "preflop"
        }
      ],
      "community_cards": [],
      "results": {
        "winners": [
          "random_bot"
        ],
        "winnings": {
          "random_bot": 30
        },
        "final_chips": {
          "conservative_bot": 40,
          "random_bot": 2930
        }
      }
    },
    {
      "hand_number": 63,
      "table_id": 1,
      "players": [
        "conservative_bot",
        "random_bot"
      ],
      "starting_chips": {
        "conservative_bot": 40,
        "random_bot": 2960
      },
      "actions": [
        {
          "player": "conservative_bot",
          "action": "fold",
          "amount": 0,
          "round": "preflop"
        }
      ],
      "community_cards": [],
      "results": {
        "winners": [
          "random_bot"
        ],
        "winnings": {
          "random_bot": 30
        },
        "final_chips": {
          "conservative_bot": 20,
          "random_bot": 2950
        }
      }
    },
    {
      "hand_number": 64,
      "table_id": 1,
      "players": [
        "conservative_bot",
        "random_bot"
      ],
      "starting_chips": {
        "conservative_bot": 20,
        "random_bot": 2980
      },
      "actions": [
        {
          "player": "conservative_bot",
          "action": "fold",
          "amount": 0,
          "round": "preflop"
        }
      ],
      "community_cards": [],
      "results": {
        "winners": [
          "random_bot"
        ],
        "winnings": {
          "random_bot": 30
        },
        "final_chips": {
          "conservative_bot": 0,
          "random_bot": 2970
        }
      }
    }
  ]
}